miketoys/__init__.py
miketoys/utils.py
miketoys-0.0.1.dist-info/licenses/LICENSE
miketoys-0.0.1.dist-info/METADATA
miketoys-0.0.1.dist-info/WHEEL
miketoys-0.0.1.dist-info/top_level.txt
miketoys-0.0.1.dist-info/RECORD
