Metadata-Version: 2.4
Name: miketoys
Version: 0.0.1
Summary: Mike's daily utils
Home-page: https://github.com/Michael-Chen1996
Author: MichaelChen
Author-email: michaelchen1996@163.com
Classifier: Programming Language :: Python :: 3
Classifier: License :: OSI Approved :: MIT License
Classifier: Operating System :: OS Independent
Requires-Python: >=3.6
License-File: LICENSE
Dynamic: author
Dynamic: author-email
Dynamic: classifier
Dynamic: description
Dynamic: description-content-type
Dynamic: home-page
Dynamic: license-file
Dynamic: requires-python
Dynamic: summary
